argparse_type_helper/__init__.py
argparse_type_helper/py.typed
argparse_type_helper/targs.py
argparse_type_helper/utils.py
argparse_type_helper-0.2.5.dist-info/licenses/LICENSE
argparse_type_helper-0.2.5.dist-info/METADATA
argparse_type_helper-0.2.5.dist-info/WHEEL
argparse_type_helper-0.2.5.dist-info/top_level.txt
argparse_type_helper-0.2.5.dist-info/RECORD
