Metadata-Version: 2.4
Name: argparse-type-helper
Version: 0.2.5
Summary: an easy-to-integrate typed argument parser
Author-email: lljbash <lljbash@gmail.com>
Project-URL: Homepage, https://github.com/lljbash/targs
Project-URL: Bug Tracker, https://github.com/lljbash/targs/issues
Keywords: argparse,typing,argument parser,type hints,typed arguments
Classifier: Development Status :: 3 - Alpha
Classifier: Environment :: Console
Classifier: Intended Audience :: Developers
Classifier: License :: OSI Approved :: MIT License
Classifier: Operating System :: POSIX
Classifier: Programming Language :: Python :: 3 :: Only
Classifier: Topic :: Software Development :: Libraries
Requires-Python: >=3.12
License-File: LICENSE
Dynamic: license-file
